.gitignore
.travis.yml
CHANGES.rst
CONTRIBUTORS.rst
MANIFEST.in
README.rst
bootstrap-buildout.py
buildout.cfg
jenkins.cfg
setup.py
buildout.d/base.cfg
buildout.d/checkouts.cfg
buildout.d/development.cfg
buildout.d/jenkins.cfg
buildout.d/sources.cfg
buildout.d/travis.cfg
buildout.d/versions.cfg
docs/LICENSE.GPL
docs/LICENSE.rst
src/collective/__init__.py
src/collective.contact.widget.egg-info/PKG-INFO
src/collective.contact.widget.egg-info/SOURCES.txt
src/collective.contact.widget.egg-info/dependency_links.txt
src/collective.contact.widget.egg-info/entry_points.txt
src/collective.contact.widget.egg-info/namespace_packages.txt
src/collective.contact.widget.egg-info/not-zip-safe
src/collective.contact.widget.egg-info/requires.txt
src/collective.contact.widget.egg-info/top_level.txt
src/collective/contact/__init__.py
src/collective/contact/widget/__init__.py
src/collective/contact/widget/configure.zcml
src/collective/contact/widget/factory.py
src/collective/contact/widget/fields.zcml
src/collective/contact/widget/interfaces.py
src/collective/contact/widget/schema.py
src/collective/contact/widget/source.py
src/collective/contact/widget/widgets.py
src/collective/contact/widget/widgets.zcml
src/collective/contact/widget/js/overlay.js.pt
src/collective/contact/widget/js/widget.js.pt
src/collective/contact/widget/locales/collective.contact.widget.pot
src/collective/contact/widget/locales/update.sh
src/collective/contact/widget/locales/es/LC_MESSAGES/collective.contact.widget.po
src/collective/contact/widget/locales/fr/LC_MESSAGES/collective.contact.widget.po
src/collective/contact/widget/profiles/default/metadata.xml
src/collective/contact/widget/profiles/default/registry.xml
src/collective/contact/widget/templates/checkbox_input.pt
src/collective/contact/widget/templates/contact_display.pt
src/collective/contact/widget/templates/contact_display_single.pt
src/collective/contact/widget/templates/contact_hidden.pt
src/collective/contact/widget/templates/contact_input.pt
src/collective/contact/widget/templates/contact_rtf.pt
src/collective/contact/widget/templates/radio_input.pt