Metadata-Version: 2.1
Name: collective.contact.widget
Version: 1.12
Summary: Contact widget
Home-page: https://github.com/collective/collective.contact.widget
Author: Vincent Fretin
Author-email: vincentfretin@ecreall.com
License: GPL
Download-URL: https://pypi.org/project/collective.contact.widget
Keywords: plone contact widget field
Platform: UNKNOWN
Classifier: Development Status :: 5 - Production/Stable
Classifier: Environment :: Web Environment
Classifier: Framework :: Plone
Classifier: Framework :: Plone :: 4.2
Classifier: Framework :: Plone :: 4.3
Classifier: License :: OSI Approved :: GNU General Public License v2 (GPLv2)
Classifier: Operating System :: OS Independent
Classifier: Programming Language :: Python
Classifier: Programming Language :: Python :: 2.7
Provides-Extra: test
